[
  {
    "timestamp": "2022-01-01T01:00:00.000Z",
    "databases": [
      { "name": "gravityr1", "sqls": [{ "sql": "SELECT name FROM users", "loadMax": 0.1, "loadSum": 0.1, "tokenizedId": "09325408F5F04845A37915E1670AFFBCXXXXXXXX" }] },
      { "name": "gravityr2", "sqls": [{ "sql": "SELECT haha FROM users", "loadMax": 0.3, "loadSum": 0.6, "tokenizedId": "CE1150D1A02A40CDB2837B94F0177ED9XXXXXXXX" }] }
    ]
  },
  {
    "timestamp": "2022-01-01T02:00:00.000Z",
    "databases": [
      {
        "name": "gravityr1",
        "sqls": [
          { "sql": "INSERT INTO tasks(user_id, title, description, status, created_at, updated_at)\nSELECT users.id,\n     'test title',\n     'test description',\n     tmp_100.id % 3,\n     users.updated_at - INTERVAL ((tmp_100.id%100) +5) HOUR,\n     users.updated_at - INTERVAL (tmp_100.id%100) HOUR\nFROM users\n     CROSS JOIN (SELECT * FROM users LIMIT 100) tmp_100", "loadMax": 0.531, "loadSum": 0.531, "tokenizedId": "70FB8D1F1B692FE0C458211B3EE75B5710E81F1C" },
          { "sql": "SELECT email FROM users", "loadMax": 0.81203, "loadSum": 0.81203, "tokenizedId": "9502706E61874BC3B22A9B09E4156984XXXXXXXX" }
        ]
      }
    ]
  },
  {
    "timestamp": "2022-01-01T03:00:00.000Z",
    "databases": [
      {
        "name": "gravityr1",
        "sqls": [
          { "sql": "SELECT name FROM users", "loadMax": 0.31234, "loadSum": 0.31234, "tokenizedId": "09325408F5F04845A37915E1670AFFBCXXXXXXXX" },
          { "sql": "SELECT email FROM users", "loadMax": 0.7534, "loadSum": 0.7534, "tokenizedId": "9502706E61874BC3B22A9B09E4156984XXXXXXXX" }
        ]
      }
    ]
  },
  {
    "timestamp": "2022-01-01T04:00:00.000Z",
    "databases": [
      {
        "name": "gravityr1",
        "sqls": [
          { "sql": "SELECT email FROM users", "loadMax": 0.71238, "loadSum": 0.71238, "tokenizedId": "9502706E61874BC3B22A9B09E4156984XXXXXXXX" },
          { "sql": "SELECT null FROM users", "loadMax": 0.002, "loadSum": 0.002, "tokenizedId": "64284C7DCCD448DA84DBF51AF490D904XXXXXXXX" },
          { "sql": "SELECT null FROM users", "loadMax": 0.005, "loadSum": 0.005, "tokenizedId": "64284C7DCCD448DA84DBF51AF490D904XXXXXXXX" }
        ]
      }
    ]
  },
  {
    "timestamp": "2022-01-01T05:00:00.000Z",
    "databases": []
  },
  {
    "timestamp": "2022-01-01T06:00:00.000Z",
    "databases": []
  },
  {
    "timestamp": "2022-01-01T07:00:00.000Z",
    "databases": []
  },
  {
    "timestamp": "2022-01-01T08:00:00.000Z",
    "databases": []
  },
  {
    "timestamp": "2022-01-01T09:00:00.000Z",
    "databases": []
  },
  {
    "timestamp": "2022-01-01T10:00:00.000Z",
    "databases": []
  },
  {
    "timestamp": "2022-01-01T11:00:00.000Z",
    "databases": []
  },
  {
    "timestamp": "2022-01-01T12:00:00.000Z",
    "databases": []
  },
  {
    "timestamp": "2022-01-01T13:00:00.000Z",
    "databases": []
  },
  {
    "timestamp": "2022-01-01T14:00:00.000Z",
    "databases": []
  },
  {
    "timestamp": "2022-01-01T15:00:00.000Z",
    "databases": []
  },
  {
    "timestamp": "2022-01-01T16:00:00.000Z",
    "databases": []
  },
  {
    "timestamp": "2022-01-01T17:00:00.000Z",
    "databases": []
  },
  {
    "timestamp": "2022-01-01T18:00:00.000Z",
    "databases": [
      {
        "name": "gravityr1",
        "sqls": [
          { "sql": "SELECT foo FROM users", "loadMax": 0.2, "loadSum": 0.2, "tokenizedId": "113A5DF0A0B24F63A62B6E5E46B0695EXXXXXXXX" },
          { "sql": "SELECT bar FROM users", "loadMax": 0.1, "loadSum": 1.0, "tokenizedId": "52981C8EEF6C4E4C8BE213ECD0766B7FXXXXXXXX" }
        ]
      }
    ]
  },
  {
    "timestamp": "2022-01-01T19:00:00.000Z",
    "databases": []
  },
  {
    "timestamp": "2022-01-01T20:00:00.000Z",
    "databases": []
  },
  {
    "timestamp": "2022-01-01T21:00:00.000Z",
    "databases": []
  },
  {
    "timestamp": "2022-01-01T22:00:00.000Z",
    "databases": []
  },
  {
    "timestamp": "2022-01-01T23:00:00.000Z",
    "databases": []
  },
  {
    "timestamp": "2022-01-02T00:00:00.000Z",
    "databases": []
  },
  {
    "timestamp": "2022-01-02T01:00:00.000Z",
    "databases": []
  },
  {
    "timestamp": "2022-01-02T02:00:00.000Z",
    "databases": []
  },
  {
    "timestamp": "2022-01-02T03:00:00.000Z",
    "databases": []
  },
  {
    "timestamp": "2022-01-02T04:00:00.000Z",
    "databases": []
  },
  {
    "timestamp": "2022-01-02T05:00:00.000Z",
    "databases": []
  },
  {
    "timestamp": "2022-01-02T06:00:00.000Z",
    "databases": []
  },
  {
    "timestamp": "2022-01-02T07:00:00.000Z",
    "databases": []
  },
  {
    "timestamp": "2022-01-02T08:00:00.000Z",
    "databases": []
  },
  {
    "timestamp": "2022-01-02T09:00:00.000Z",
    "databases": []
  },
  {
    "timestamp": "2022-01-02T10:00:00.000Z",
    "databases": []
  },
  {
    "timestamp": "2022-01-02T11:00:00.000Z",
    "databases": []
  },
  {
    "timestamp": "2022-01-02T12:00:00.000Z",
    "databases": []
  },
  {
    "timestamp": "2022-01-02T13:00:00.000Z",
    "databases": []
  },
  {
    "timestamp": "2022-01-02T14:00:00.000Z",
    "databases": []
  },
  {
    "timestamp": "2022-01-02T15:00:00.000Z",
    "databases": []
  },
  {
    "timestamp": "2022-01-02T16:00:00.000Z",
    "databases": []
  },
  {
    "timestamp": "2022-01-02T17:00:00.000Z",
    "databases": []
  },
  {
    "timestamp": "2022-01-02T18:00:00.000Z",
    "databases": []
  },
  {
    "timestamp": "2022-01-02T19:00:00.000Z",
    "databases": []
  },
  {
    "timestamp": "2022-01-02T20:00:00.000Z",
    "databases": []
  },
  {
    "timestamp": "2022-01-02T21:00:00.000Z",
    "databases": []
  },
  {
    "timestamp": "2022-01-02T22:00:00.000Z",
    "databases": []
  },
  {
    "timestamp": "2022-01-02T23:00:00.000Z",
    "databases": []
  },
  {
    "timestamp": "2022-01-03T00:00:00.000Z",
    "databases": []
  },
  {
    "timestamp": "2022-01-03T01:00:00.000Z",
    "databases": []
  },
  {
    "timestamp": "2022-01-03T02:00:00.000Z",
    "databases": []
  },
  {
    "timestamp": "2022-01-03T03:00:00.000Z",
    "databases": []
  },
  {
    "timestamp": "2022-01-03T04:00:00.000Z",
    "databases": []
  },
  {
    "timestamp": "2022-01-03T05:00:00.000Z",
    "databases": []
  },
  {
    "timestamp": "2022-01-03T06:00:00.000Z",
    "databases": []
  },
  {
    "timestamp": "2022-01-03T07:00:00.000Z",
    "databases": []
  },
  {
    "timestamp": "2022-01-03T08:00:00.000Z",
    "databases": []
  },
  {
    "timestamp": "2022-01-03T09:00:00.000Z",
    "databases": []
  },
  {
    "timestamp": "2022-01-03T10:00:00.000Z",
    "databases": []
  },
  {
    "timestamp": "2022-01-03T11:00:00.000Z",
    "databases": []
  },
  {
    "timestamp": "2022-01-03T12:00:00.000Z",
    "databases": []
  },
  {
    "timestamp": "2022-01-03T13:00:00.000Z",
    "databases": []
  },
  {
    "timestamp": "2022-01-03T14:00:00.000Z",
    "databases": []
  },
  {
    "timestamp": "2022-01-03T15:00:00.000Z",
    "databases": []
  },
  {
    "timestamp": "2022-01-03T16:00:00.000Z",
    "databases": []
  },
  {
    "timestamp": "2022-01-03T17:00:00.000Z",
    "databases": []
  },
  {
    "timestamp": "2022-01-03T18:00:00.000Z",
    "databases": []
  },
  {
    "timestamp": "2022-01-03T19:00:00.000Z",
    "databases": []
  },
  {
    "timestamp": "2022-01-03T20:00:00.000Z",
    "databases": []
  },
  {
    "timestamp": "2022-01-03T21:00:00.000Z",
    "databases": []
  },
  {
    "timestamp": "2022-01-03T22:00:00.000Z",
    "databases": []
  },
  {
    "timestamp": "2022-01-03T23:00:00.000Z",
    "databases": []
  },
  {
    "timestamp": "2022-01-04T00:00:00.000Z",
    "databases": []
  },
  {
    "timestamp": "2022-01-04T01:00:00.000Z",
    "databases": []
  },
  {
    "timestamp": "2022-01-04T02:00:00.000Z",
    "databases": []
  },
  {
    "timestamp": "2022-01-04T03:00:00.000Z",
    "databases": []
  },
  {
    "timestamp": "2022-01-04T04:00:00.000Z",
    "databases": []
  },
  {
    "timestamp": "2022-01-04T05:00:00.000Z",
    "databases": []
  },
  {
    "timestamp": "2022-01-04T06:00:00.000Z",
    "databases": []
  },
  {
    "timestamp": "2022-01-04T07:00:00.000Z",
    "databases": []
  },
  {
    "timestamp": "2022-01-04T08:00:00.000Z",
    "databases": []
  },
  {
    "timestamp": "2022-01-04T09:00:00.000Z",
    "databases": []
  },
  {
    "timestamp": "2022-01-04T10:00:00.000Z",
    "databases": []
  },
  {
    "timestamp": "2022-01-04T11:00:00.000Z",
    "databases": []
  },
  {
    "timestamp": "2022-01-04T12:00:00.000Z",
    "databases": []
  },
  {
    "timestamp": "2022-01-04T13:00:00.000Z",
    "databases": []
  },
  {
    "timestamp": "2022-01-04T14:00:00.000Z",
    "databases": []
  },
  {
    "timestamp": "2022-01-04T15:00:00.000Z",
    "databases": []
  },
  {
    "timestamp": "2022-01-04T16:00:00.000Z",
    "databases": []
  },
  {
    "timestamp": "2022-01-04T17:00:00.000Z",
    "databases": []
  },
  {
    "timestamp": "2022-01-04T18:00:00.000Z",
    "databases": []
  },
  {
    "timestamp": "2022-01-04T19:00:00.000Z",
    "databases": []
  },
  {
    "timestamp": "2022-01-04T20:00:00.000Z",
    "databases": []
  },
  {
    "timestamp": "2022-01-04T21:00:00.000Z",
    "databases": []
  },
  {
    "timestamp": "2022-01-04T22:00:00.000Z",
    "databases": []
  },
  {
    "timestamp": "2022-01-04T23:00:00.000Z",
    "databases": []
  },
  {
    "timestamp": "2022-01-05T00:00:00.000Z",
    "databases": []
  },
  {
    "timestamp": "2022-01-05T01:00:00.000Z",
    "databases": []
  },
  {
    "timestamp": "2022-01-05T02:00:00.000Z",
    "databases": []
  },
  {
    "timestamp": "2022-01-05T03:00:00.000Z",
    "databases": []
  },
  {
    "timestamp": "2022-01-05T04:00:00.000Z",
    "databases": []
  },
  {
    "timestamp": "2022-01-05T05:00:00.000Z",
    "databases": []
  },
  {
    "timestamp": "2022-01-05T06:00:00.000Z",
    "databases": []
  },
  {
    "timestamp": "2022-01-05T07:00:00.000Z",
    "databases": []
  },
  {
    "timestamp": "2022-01-05T08:00:00.000Z",
    "databases": []
  },
  {
    "timestamp": "2022-01-05T09:00:00.000Z",
    "databases": []
  },
  {
    "timestamp": "2022-01-05T10:00:00.000Z",
    "databases": []
  },
  {
    "timestamp": "2022-01-05T11:00:00.000Z",
    "databases": []
  },
  {
    "timestamp": "2022-01-05T12:00:00.000Z",
    "databases": []
  },
  {
    "timestamp": "2022-01-05T13:00:00.000Z",
    "databases": []
  },
  {
    "timestamp": "2022-01-05T14:00:00.000Z",
    "databases": []
  },
  {
    "timestamp": "2022-01-05T15:00:00.000Z",
    "databases": []
  },
  {
    "timestamp": "2022-01-05T16:00:00.000Z",
    "databases": []
  },
  {
    "timestamp": "2022-01-05T17:00:00.000Z",
    "databases": []
  },
  {
    "timestamp": "2022-01-05T18:00:00.000Z",
    "databases": []
  },
  {
    "timestamp": "2022-01-05T19:00:00.000Z",
    "databases": []
  },
  {
    "timestamp": "2022-01-05T20:00:00.000Z",
    "databases": []
  },
  {
    "timestamp": "2022-01-05T21:00:00.000Z",
    "databases": []
  },
  {
    "timestamp": "2022-01-05T22:00:00.000Z",
    "databases": []
  },
  {
    "timestamp": "2022-01-05T23:00:00.000Z",
    "databases": []
  },
  {
    "timestamp": "2022-01-06T00:00:00.000Z",
    "databases": []
  },
  {
    "timestamp": "2022-01-06T01:00:00.000Z",
    "databases": []
  },
  {
    "timestamp": "2022-01-06T02:00:00.000Z",
    "databases": []
  },
  {
    "timestamp": "2022-01-06T03:00:00.000Z",
    "databases": []
  },
  {
    "timestamp": "2022-01-06T04:00:00.000Z",
    "databases": []
  },
  {
    "timestamp": "2022-01-06T05:00:00.000Z",
    "databases": []
  },
  {
    "timestamp": "2022-01-06T06:00:00.000Z",
    "databases": []
  },
  {
    "timestamp": "2022-01-06T07:00:00.000Z",
    "databases": []
  },
  {
    "timestamp": "2022-01-06T08:00:00.000Z",
    "databases": []
  },
  {
    "timestamp": "2022-01-06T09:00:00.000Z",
    "databases": []
  },
  {
    "timestamp": "2022-01-06T10:00:00.000Z",
    "databases": []
  },
  {
    "timestamp": "2022-01-06T11:00:00.000Z",
    "databases": [
      {
        "name": "gravityr1",
        "sqls": [
          { "sql": "SELECT name FROM users", "loadMax": 0.231, "loadSum": 0.231, "tokenizedId": "D457B102376343DE92F6E87DCD53EC9BXXXXXXXX" },
          { "sql": "SELECT email FROM users", "loadMax": 0.81203, "loadSum": 0.81203, "tokenizedId": "9502706E61874BC3B22A9B09E4156984XXXXXXXX" }
        ]
      }
    ]
  },
  {
    "timestamp": "2022-01-06T12:00:00.000Z",
    "databases": []
  },
  {
    "timestamp": "2022-01-06T13:00:00.000Z",
    "databases": []
  },
  {
    "timestamp": "2022-01-06T14:00:00.000Z",
    "databases": []
  },
  {
    "timestamp": "2022-01-06T15:00:00.000Z",
    "databases": []
  },
  {
    "timestamp": "2022-01-06T16:00:00.000Z",
    "databases": []
  },
  {
    "timestamp": "2022-01-06T17:00:00.000Z",
    "databases": [
      {
        "name": "gravityr1",
        "sqls": [
          {
            "sql": "INSERT INTO tasks(user_id, title, description, status, created_at, updated_at)\nSELECT users.id,\n     'test title',\n     'test description',\n     tmp_100.id % 3,\n     users.updated_at - INTERVAL ((tmp_100.id%100) +5) HOUR,\n     users.updated_at - INTERVAL (tmp_100.id%100) HOUR\nFROM users\n     CROSS JOIN (SELECT * FROM users LIMIT 100) tmp_100",
            "loadMax": 0.18661971830985916,
            "loadSum": 0.18661971830985916,
            "tokenizedId": "70FB8D1F1B692FE0C458211B3EE75B5710E81F1C"
          },
          {
            "sql": "explain analyze SELECT name, t.description FROM users INNER JOIN tasks AS t ON users.id = t.user_id WHERE users.email = 'test31776@example.com'",
            "loadMax": 0.078125,
            "loadSum": 0.078125,
            "tokenizedId": "64E6FE2C360536B8BED607E6A6B66BC463667A4A"
          },
          {
            "sql": "SELECT name, t.description FROM users INNER JOIN tasks AS t ON users.id = t.user_id WHERE users.email = 'test31779@example.com'",
            "loadMax": 0.0234375,
            "loadSum": 0.0234375,
            "tokenizedId": "D51E26E104C8374C3547D9AEC929104FB6A2D9AE"
          },
          {
            "sql": "SELECT\nname,\nt.description\nFROM\nusers\nINNER JOIN tasks AS t ON users.id = t.user_id\nWHERE\nusers.email = 'test31776@example.com'",
            "loadMax": 0.01171875,
            "loadSum": 0.01171875,
            "tokenizedId": "D51E26E104C8374C3547D9AEC929104FB6A2D9AE"
          },
          {
            "sql": "INSERT users(name, email, password, created_at, updated_at)\nWITH l0 AS (SELECT 0 AS num UNION ALL SELECT 1),\n     l1 AS (SELECT a.num * 2 + b.num AS num FROM l0 AS a CROSS JOIN l0 AS b),\n     l2 AS (SELECT a.num * 4 + b.num AS num FROM l1 AS a CROSS JOIN l1 AS b),\n     l3 AS (SELECT a.num * 16 + b.num AS num FROM l2 AS a CROSS JOIN l2 AS b),\n     l4 AS (SELECT a.num * 256 + b.num AS num FROM l3 AS a CROSS JOIN l3 AS b)\nSELECT CONCAT('test', CAST(num AS char)),\n       CONCAT('test', CAST(num AS c",
            "loadMax": 0.007042253521126761,
            "loadSum": 0.007042253521126761,
            "tokenizedId": "E11B0E9BBC156D4CFE99F1530946C682D27FD626"
          },
          {
            "sql": "select @@version_comment limit 1",
            "loadMax": 0.0035211267605633804,
            "loadSum": 0.0035211267605633804,
            "tokenizedId": "AC5AB727A800FAB79DF2B4A3EDE4CBBAB9FB4C25"
          }
        ]
      }
    ]
  },
  {
    "timestamp": "2022-01-06T18:00:00.000Z",
    "databases": []
  },
  {
    "timestamp": "2022-01-06T19:00:00.000Z",
    "databases": []
  },
  {
    "timestamp": "2022-01-06T20:00:00.000Z",
    "databases": []
  },
  {
    "timestamp": "2022-01-06T21:00:00.000Z",
    "databases": []
  },
  {
    "timestamp": "2022-01-06T22:00:00.000Z",
    "databases": []
  },
  {
    "timestamp": "2022-01-06T23:00:00.000Z",
    "databases": []
  },
  {
    "timestamp": "2022-01-07T00:00:00.000Z",
    "databases": []
  },
  {
    "timestamp": "2022-01-07T01:00:00.000Z",
    "databases": []
  },
  {
    "timestamp": "2022-01-07T02:00:00.000Z",
    "databases": []
  },
  {
    "timestamp": "2022-01-07T03:00:00.000Z",
    "databases": []
  },
  {
    "timestamp": "2022-01-07T04:00:00.000Z",
    "databases": []
  },
  {
    "timestamp": "2022-01-07T05:00:00.000Z",
    "databases": []
  },
  {
    "timestamp": "2022-01-07T06:00:00.000Z",
    "databases": []
  },
  {
    "timestamp": "2022-01-07T07:00:00.000Z",
    "databases": []
  },
  {
    "timestamp": "2022-01-07T08:00:00.000Z",
    "databases": []
  },
  {
    "timestamp": "2022-01-07T09:00:00.000Z",
    "databases": []
  },
  {
    "timestamp": "2022-01-07T10:00:00.000Z",
    "databases": []
  },
  {
    "timestamp": "2022-01-07T11:00:00.000Z",
    "databases": []
  },
  {
    "timestamp": "2022-01-07T12:00:00.000Z",
    "databases": []
  },
  {
    "timestamp": "2022-01-07T13:00:00.000Z",
    "databases": []
  },
  {
    "timestamp": "2022-01-07T14:00:00.000Z",
    "databases": []
  },
  {
    "timestamp": "2022-01-07T15:00:00.000Z",
    "databases": []
  },
  {
    "timestamp": "2022-01-07T16:00:00.000Z",
    "databases": []
  },
  {
    "timestamp": "2022-01-07T17:00:00.000Z",
    "databases": []
  },
  {
    "timestamp": "2022-01-07T18:00:00.000Z",
    "databases": []
  },
  {
    "timestamp": "2022-01-07T19:00:00.000Z",
    "databases": []
  },
  {
    "timestamp": "2022-01-07T20:00:00.000Z",
    "databases": []
  },
  {
    "timestamp": "2022-01-07T21:00:00.000Z",
    "databases": []
  },
  {
    "timestamp": "2022-01-07T22:00:00.000Z",
    "databases": [
      {
        "name": "gravityr1",
        "sqls": [
          { "sql": "SELECT name FROM users", "loadMax": 0.231, "loadSum": 0.231, "tokenizedId": "D457B102376343DE92F6E87DCD53EC9BXXXXXXXX" },
          { "sql": "SELECT email FROM users", "loadMax": 0.81203, "loadSum": 0.81203, "tokenizedId": "9502706E61874BC3B22A9B09E4156984XXXXXXXX" }
        ]
      }
    ]
  },
  {
    "timestamp": "2022-01-07T23:00:00.000Z",
    "databases": [
      {
        "name": "gravityr1",
        "sqls": [
          { "sql": "SELECT name FROM users", "loadMax": 0.231, "loadSum": 0.231, "tokenizedId": "D457B102376343DE92F6E87DCD53EC9BXXXXXXXX" },
          { "sql": "SELECT email FROM users", "loadMax": 0.81203, "loadSum": 0.81203, "tokenizedId": "9502706E61874BC3B22A9B09E4156984XXXXXXXX" }
        ]
      }
    ]
  },
  {
    "timestamp": "2022-01-08T00:00:00.000Z",
    "databases": [
      {
        "name": "gravityr1",
        "sqls": [
          { "sql": "SELECT name FROM users", "loadMax": 0.231, "loadSum": 0.231, "tokenizedId": "D457B102376343DE92F6E87DCD53EC9BXXXXXXXX" },
          { "sql": "SELECT email FROM users", "loadMax": 0.81203, "loadSum": 0.81203, "tokenizedId": "9502706E61874BC3B22A9B09E4156984XXXXXXXX" }
        ]
      }
    ]
  }
]
